README
setup.py
DeepDesk.egg-info/PKG-INFO
DeepDesk.egg-info/SOURCES.txt
DeepDesk.egg-info/dependency_links.txt
DeepDesk.egg-info/requires.txt
DeepDesk.egg-info/top_level.txt
deepdesk/__init__.py
deepdesk/data.py
deepdesk/uwsgi_server.py