Metadata-Version: 1.1
Name: DeepDesk
Version: 0.1.0
Summary: Flexible data storage, with indexing, templates and validation
Home-page: https://bitbucket.org/Domino_Marama/deepdesk
Author: Domino Marama
Author-email: domino@dominodesigns.info
License: UNKNOWN
Keywords: deepdesk json index validate storage database
Platform: UNKNOWN
Classifier: Development Status :: 3 - Alpha
Classifier: Intended Audience :: Developers
Classifier: License :: OSI Approved :: GNU Affero General Public License v3 or later (AGPLv3+)
Classifier: Operating System :: POSIX :: Linux
Classifier: Programming Language :: Python :: 3.3
Classifier: Topic :: Database :: Database Engines/Servers
Classifier: Topic :: Text Processing
Classifier: Topic :: Text Processing :: Indexing
